awstanding/__init__.py
awstanding/exceptions.py
awstanding/parameter_store.py
awstanding/s3.py
awstanding-1.2.0.dist-info/LICENCE
awstanding-1.2.0.dist-info/METADATA
awstanding-1.2.0.dist-info/WHEEL
awstanding-1.2.0.dist-info/top_level.txt
awstanding-1.2.0.dist-info/RECORD
