Metadata-Version: 2.1
Name: awstanding
Version: 1.2.0
Summary: Load parameters from AWS Parameter Store
Home-page: https://github.com/jiss2891/awstanding
Author: Juan Ignacio Sánchez Sampayo
Author-email: jiss2891@gmail.com
License: UNKNOWN
Project-URL: Bug Tracker, https://github.com/jiss2891/awstanding/issues
Platform: UNKNOWN
Classifier: Programming Language :: Python :: 3
Classifier: License :: OSI Approved :: GNU General Public License v3 (GPLv3)
Classifier: Operating System :: OS Independent
Requires-Python: >=3.6
License-File: LICENCE
